Metadata-Version: 2.4
Name: image_processing_b
Version: 0.0.1
Summary: Image Processing Package using skimage
Home-page: https://github.com/bradbrasil/image-processing-package
Author: Brad
Requires-Python: >=3.5
Requires-Dist: matplotlib
Requires-Dist: numpy
Requires-Dist: scikit-image>=0.16.1
Dynamic: author
Dynamic: description
Dynamic: description-content-type
Dynamic: home-page
Dynamic: requires-dist
Dynamic: requires-python
Dynamic: summary
